datafreeze/__init__.py
datafreeze/app.py
datafreeze/config.py
datafreeze/util.py
datafreeze/format/__init__.py
datafreeze/format/common.py
datafreeze/format/fcsv.py
datafreeze/format/fjson.py
datafreeze/format/ftabson.py
datafreeze-0.1.0.dist-info/DESCRIPTION.rst
datafreeze-0.1.0.dist-info/METADATA
datafreeze-0.1.0.dist-info/RECORD
datafreeze-0.1.0.dist-info/WHEEL
datafreeze-0.1.0.dist-info/entry_points.txt
datafreeze-0.1.0.dist-info/metadata.json
datafreeze-0.1.0.dist-info/namespace_packages.txt
datafreeze-0.1.0.dist-info/top_level.txt
