Metadata-Version: 1.1
Name: datafreeze
Version: 0.1.0
Summary: Export data from a SQL database to a set of file formats.
Home-page: http://github.com/pudo/datafreeze
Author: Friedrich Lindenberg, Gregor Aisch, Stefan Wehrmeyer
Author-email: friedrich@pudo.org
License: MIT
Keywords: sql sqlalchemy etl loading utility
Platform: UNKNOWN
Classifier: Development Status :: 3 - Alpha
Classifier: Intended Audience :: Developers
Classifier: License :: OSI Approved :: MIT License
Classifier: Operating System :: OS Independent
Classifier: Programming Language :: Python :: 2.7
Classifier: Programming Language :: Python :: 3.3
Classifier: Programming Language :: Python :: 3.4
Classifier: Programming Language :: Python :: 3.5
